tensorflow/__init__.py
tensorflow/core/__init__.py
tensorflow/core/example/__init__.py
tensorflow/core/example/example_pb2.py
tensorflow/core/example/feature_pb2.py
tensorflow/core/framework/__init__.py
tensorflow/core/framework/allocation_description_pb2.py
tensorflow/core/framework/attr_value_pb2.py
tensorflow/core/framework/cost_graph_pb2.py
tensorflow/core/framework/function_pb2.py
tensorflow/core/framework/graph_pb2.py
tensorflow/core/framework/node_def_pb2.py
tensorflow/core/framework/op_def_pb2.py
tensorflow/core/framework/resource_handle_pb2.py
tensorflow/core/framework/step_stats_pb2.py
tensorflow/core/framework/tensor_description_pb2.py
tensorflow/core/framework/tensor_pb2.py
tensorflow/core/framework/tensor_shape_pb2.py
tensorflow/core/framework/types_pb2.py
tensorflow/core/framework/variable_pb2.py
tensorflow/core/framework/versions_pb2.py
tensorflow/core/protobuf/__init__.py
tensorflow/core/protobuf/cluster_pb2.py
tensorflow/core/protobuf/config_pb2.py
tensorflow/core/protobuf/debug_pb2.py
tensorflow/core/protobuf/error_codes_pb2.py
tensorflow/core/protobuf/meta_graph_pb2.py
tensorflow/core/protobuf/named_tensor_pb2.py
tensorflow/core/protobuf/rewriter_config_pb2.py
tensorflow/core/protobuf/saved_object_graph_pb2.py
tensorflow/core/protobuf/saver_pb2.py
tensorflow/core/protobuf/struct_pb2.py
tensorflow/core/protobuf/trackable_object_graph_pb2.py
tensorflow/core/protobuf/verifier_config_pb2.py
tensorflow_serving/__init__.py
tensorflow_serving/apis/__init__.py
tensorflow_serving/apis/classification_pb2.py
tensorflow_serving/apis/get_model_metadata_pb2.py
tensorflow_serving/apis/get_model_status_pb2.py
tensorflow_serving/apis/inference_pb2.py
tensorflow_serving/apis/input_pb2.py
tensorflow_serving/apis/model_management_pb2.py
tensorflow_serving/apis/model_pb2.py
tensorflow_serving/apis/model_service_pb2.py
tensorflow_serving/apis/model_service_pb2_grpc.py
tensorflow_serving/apis/predict_pb2.py
tensorflow_serving/apis/prediction_service_pb2.py
tensorflow_serving_client_grpc-2.3.0.dist-info/LICENSE
tensorflow_serving_client_grpc-2.3.0.dist-info/METADATA
tensorflow_serving_client_grpc-2.3.0.dist-info/WHEEL
tensorflow_serving_client_grpc-2.3.0.dist-info/__init__.py
tensorflow_serving_client_grpc-2.3.0.dist-info/top_level.txt
tensorflow_serving_client_grpc-2.3.0.dist-info/RECORD
