Metadata-Version: 2.1
Name: tensorflow-serving-client-grpc
Version: 2.3.0
Summary: A prebuilt tensorflow serving client from the tensorflow serving proto files
Home-page: https://github.com/figroc/tensorflow-serving-client
Author: Figroc Chen
Author-email: figroc@gmail.com
License: Apache-2.0
Platform: any
Classifier: Development Status :: 5 - Production/Stable
Classifier: Intended Audience :: Developers
Classifier: License :: OSI Approved :: Apache Software License
Classifier: Operating System :: OS Independent
Classifier: Programming Language :: Python :: 3
Classifier: Topic :: Scientific/Engineering :: Artificial Intelligence
Classifier: Topic :: Software Development :: Libraries :: Python Modules
Requires-Python: >=3.5
Requires-Dist: grpcio
Requires-Dist: protobuf
